mite_vspkg/__init__.py
mite_vspkg/__main__.py
mite_vspkg/config.py.default
mite_vspkg/lib/__init__.py
mite_vspkg/lib/vsdownload.py
mite_vspkg/src/__init__.py
mite_vspkg/src/func/__init__.py
mite_vspkg/src/func/func_check_files.py
mite_vspkg/src/func/func_download_unpack.py
mite_vspkg/src/func/func_parse_out.py
mite_vspkg/src/func/func_print_deps.py
mite_vspkg/src/func/func_print_sel.py
mite_vspkg/src/util/__init__.py
mite_vspkg/src/util/util_args.py
mite_vspkg/src/util/util_const.py
mite_vspkg/src/util/util_enum.py
mite_vspkg/src/util/util_filter.py
mite_vspkg/src/util/util_json.py
mite_vspkg/src/util/util_load_cfg.py
mite_vspkg/src/util/util_msi.py
mite_vspkg/src/util/util_vsmanifest.py
mite_vspkg-1.0.1.dist-info/LICENSE
mite_vspkg-1.0.1.dist-info/METADATA
mite_vspkg-1.0.1.dist-info/WHEEL
mite_vspkg-1.0.1.dist-info/top_level.txt
mite_vspkg-1.0.1.dist-info/RECORD
