Metadata-Version: 2.1
Name: mite-vspkg
Version: 1.0.1
Summary: A utility to get a list of files per Visual Studio installer package and to unpack Visual Studio installer packages.
Home-page: https://github.com/mite-user/mite-vspkg
Author: mite-user
Author-email: mite-user@protonmail.com
Classifier: Development Status :: 5 - Production/Stable
Classifier: Environment :: Console
Classifier: Intended Audience :: Developers
Classifier: License :: OSI Approved :: ISC License (ISCL)
Classifier: Operating System :: OS Independent
Classifier: Programming Language :: Python :: 3
Classifier: Topic :: Software Development
Requires-Python: >=3.7
License-File: LICENSE
